pyunit_phone/__init__.py
pyunit_phone/phone.py
pyunit_phone/phoneRegularity.py
pyunit_phone/singleton.py
pyunit_phone/telephone.zip
pyunit_phone-2020.6.28.dist-info/LICENSE
pyunit_phone-2020.6.28.dist-info/METADATA
pyunit_phone-2020.6.28.dist-info/WHEEL
pyunit_phone-2020.6.28.dist-info/top_level.txt
pyunit_phone-2020.6.28.dist-info/RECORD
