Metadata-Version: 2.1
Name: pyunit-phone
Version: 2020.6.28
Summary: 提取电话信息
Home-page: https://github.com/PyUnit/pyunit-phone
Author: Jtyoui
Author-email: jtyoui@qq.com
License: MIT Licence
Platform: any
Classifier: Programming Language :: Python :: 3
Classifier: License :: OSI Approved :: MIT License
Classifier: Operating System :: OS Independent
